{
  "kind": "build_request",
  "title": "Add crackers burst, improve letter contrast, add kiss pattern, fix butterfly rendering",
  "projectName": "Romantic Birthday",
  "priority": "normal",
  "requirements": [
    {
      "id": "REQ-1",
      "text": "Add a crackers burst animation effect that plays at an appropriate moment in the experience (e.g., during intro or transition)",
      "target": "frontend",
      "source": {
        "messageIds": [
          "msg-current"
        ],
        "quotes": [
          "I want crackers burst"
        ]
      },
      "acceptanceCriteria": [
        "Crackers burst animation is visible and plays at least once",
        "Animation timing fits naturally within the existing flow",
        "Visual effect is celebratory and matches the romantic theme"
      ]
    },
    {
      "id": "REQ-2",
      "text": "Ensure letter text has sufficient contrast against the background so it is not camouflaged and remains clearly readable",
      "target": "frontend",
      "source": {
        "messageIds": [
          "msg-current"
        ],
        "quotes": [
          "the letters must not be camouflaged in background"
        ]
      },
      "acceptanceCriteria": [
        "Letter text is clearly visible against pink gradient background",
        "Text contrast meets readability standards",
        "Text remains legible throughout all animations"
      ]
    },
    {
      "id": "REQ-3",
      "text": "Fill the letter area with kiss graphics as a background pattern that does not obscure or hide the text content",
      "target": "frontend",
      "source": {
        "messageIds": [
          "msg-current"
        ],
        "quotes": [
          "the letter must be filled with kisses that is in the background and does not hide words"
        ]
      },
      "acceptanceCriteria": [
        "Kiss graphics appear as a subtle background pattern within the letter area",
        "All letter text remains fully readable over the kiss pattern",
        "Kiss graphics enhance rather than compete with the text"
      ]
    },
    {
      "id": "REQ-4",
      "text": "Fix butterfly rendering so they display as proper butterfly shapes instead of boxes",
      "target": "frontend",
      "source": {
        "messageIds": [
          "msg-current"
        ],
        "quotes": [
          "the butterflies must not be boxes"
        ]
      },
      "acceptanceCriteria": [
        "Butterflies render as recognizable butterfly shapes",
        "No box-like artifacts or placeholder shapes appear",
        "Butterfly images load correctly and display smoothly"
      ]
    }
  ],
  "constraints": [
    "Do not change the backend implementation",
    "Maintain existing pink gradient background",
    "Preserve existing music controls and interactive question flow",
    "Keep the romantic birthday microsite theme intact"
  ],
  "nonGoals": [
    "Changing the overall color scheme from pink",
    "Modifying the core question/answer flow logic",
    "Adding new interactive features beyond requested fixes",
    "Redesigning the envelope reveal animation"
  ],
  "imageRequirements": {
    "required": [
      "Decorative kiss mark icon in romantic style suitable for pattern background (kiss-mark.dim_64x64.png)"
    ],
    "edits": []
  }
}